{
  "$schema": "https://biomejs.dev/schemas/2.4.6/schema.json",
  "vcs": {
    "enabled": true,
    "clientKind": "git",
    "useIgnoreFile": true
  },
  "files": {
    "ignoreUnknown": true,
    "includes": ["packages/*/src/**/*.ts", "packages/*/src/**/*.tsx", "*.json"]
  },
  "formatter": {
    "enabled": true,
    "indentStyle": "space",
    "indentWidth": 2,
    "lineWidth": 120
  },
  "linter": {
    "enabled": true,
    "rules": {
      "recommended": true,
      "suspicious": {
        "noExplicitAny": "off",
        "noShadowRestrictedNames": "off",
        "noImplicitAnyLet": "off",
        "noTemplateCurlyInString": "off",
        "noAssignInExpressions": "off",
        "useIterableCallbackReturn": "off"
      },
      "style": {
        "noNonNullAssertion": "off",
        "useImportType": "error",
        "useTemplate": "off"
      },
      "complexity": {
        "noForEach": "off",
        "useLiteralKeys": "off",
        "noStaticOnlyClass": "off",
        "noBannedTypes": "off"
      },
      "correctness": {
        "noUnusedImports": "warn",
        "noUnusedVariables": "warn",
        "noUnusedFunctionParameters": "off",
        "noUnusedPrivateClassMembers": "warn",
        "noUnsafeFinally": "off"
      }
    }
  },
  "javascript": {
    "formatter": {
      "quoteStyle": "double",
      "trailingCommas": "all"
    }
  },
  "assist": {
    "enabled": true,
    "actions": {
      "source": {
        "organizeImports": "on"
      }
    }
  }
}
